datapath_controller/HCF_finder.v
module pipo (
    output reg [15:0] aout, input [15:0] a, input clk, lda
);
    initial aout = 0;
    always @(posedge clk ) begin
        if (lda) aout <= a;
    end
endmodule

module subtractor (
    output reg [15:0] subout, input [15:0] a, b
);
    always @(*) begin
        subout = a - b;
    end
endmodule

module comp (
    output lt,gt,et, input [15:0] aout, bout
);
    assign lt = aout < bout; assign gt = aout > bout; assign et = (aout == bout);
endmodule

module mux (
    output [15:0] out, input [15:0] in1, in2, input sel
);   
    assign out = sel ? in1:in2;
endmodule

module datapath_hcf (result1,result2, lt,gt,et, lda,ldb,sel1,sel2,sel_in,clk, data_in);
    output [15:0] result1,result2; output lt,gt,et; input lda,ldb,sel1,sel2,sel_in,clk; input [15:0] data_in;
    wire [15:0] aout, bout, a,b,subout, data; assign result1 = aout, result2 = bout;
    pipo A(aout, data, clk, lda);
    pipo B(bout, data, clk, ldb);
    subtractor S(subout, a, b);
    comp C(lt,gt,et,aout,bout);
    mux M0(a, aout, bout, sel1);
    mux M1(b, aout, bout, sel2);
    mux M2(data, subout, data_in, sel_in);
endmodule

module control_hcf (st,lda, ldb, sel1, sel2, sel_in, done, start, lt,gt,et,clk);
    output reg lda,ldb,sel1,sel2,sel_in, done; input start, lt,gt,et,clk; output [2:0] st;
    reg [2:0] state; reg [15:0] aout,bout;
    parameter s0 = 0,s1 = 1, s2 = 2, s3 = 3, s4 = 4, s5 = 5; assign st = state;
    always @(posedge clk ) begin
        case (state)
                s0 : if (start) state <= s1;
                s1 : state <= s2;
                s2 : #2 if (et) state <= s5;
                    else if (lt) state <= s3;
                    else if (gt) state <= s4;

                s3 : #2 if (et) state <= s5;
                    else if (lt) state <= s3;
                    else if (gt) state <= s4;

                s4: #2 if (et) state <= s5;
                    else if (lt) state <= s3;
                    else if (gt) state <= s4;              
    
                s5 : state <= s5;
            default: state <= s0;
        endcase
    end

    always @(state) begin
        
        case (state)
                s0 : begin lda = 0; ldb = 0; sel1 = 0; sel2 = 0; sel_in = 0; done = 0; end
                s1 : begin lda = 1; ldb = 0; sel1 = 0; sel2 = 0; sel_in = 0; done = 0; end
                s2 : begin lda = 0; ldb = 1; sel1 = 0; sel2 = 0; sel_in = 0; done = 0; end
                s3 : begin lda = 0; ldb = 1; sel1 = 0; sel2 = 1; sel_in = 1; done = 0; end 
                s4 : begin lda = 1; ldb = 0; sel1 = 1; sel2 = 0; sel_in = 1; done = 0; end
                s5 : begin lda = 0; ldb = 0; sel1 = 0; sel2 = 0; sel_in = 0; done = 1; end
            default: begin lda = 0; ldb = 0; sel1 = 0; sel2 = 0; sel_in = 0; done = 0; end
        endcase 
    end
endmodule

module hcf_testbench;
    wire done; reg [15:0] data_in; reg clk,start; wire [15:0] result1,result2; wire [2:0] st;
    datapath_hcf DH(result1, result2, lt,gt,et, lda,ldb,sel1,sel2,sel_in,clk, data_in);
    control_hcf CH(st,lda, ldb, sel1, sel2, sel_in, done, start, lt,gt,et,clk);
    initial begin
        clk = 0;
        #3 start = 1;
        #100 $finish;
    end
always #5 clk=~clk;
    initial begin
        $dumpfile("hcf_finder.vcd");
        $dumpvars(0,hcf_testbench);
        #17 data_in=7;
        #10 data_in=3;
        $monitor($time, "%d %d %b", result1, result2, done);
    end
endmodule

build/hcf_finder.vcd
$date
	Tue Sep  9 00:43:22 2025
$end
$version
	Icarus Verilog
$end
$timescale
	1s
$end
$scope module hcf_testbench $end
$var wire 3 ! st [2:0] $end
$var wire 1 " sel_in $end
$var wire 1 # sel2 $end
$var wire 1 $ sel1 $end
$var wire 16 % result2 [15:0] $end
$var wire 16 & result1 [15:0] $end
$var wire 1 ' lt $end
$var wire 1 ( ldb $end
$var wire 1 ) lda $end
$var wire 1 * gt $end
$var wire 1 + et $end
$var wire 1 , done $end
$var reg 1 - clk $end
$var reg 16 . data_in [15:0] $end
$var reg 1 / start $end
$scope module CH $end
$var wire 1 - clk $end
$var wire 3 0 st [2:0] $end
$var wire 1 / start $end
$var wire 1 ' lt $end
$var wire 1 * gt $end
$var wire 1 + et $end
$var parameter 32 1 s0 $end
$var parameter 32 2 s1 $end
$var parameter 32 3 s2 $end
$var parameter 32 4 s3 $end
$var parameter 32 5 s4 $end
$var parameter 32 6 s5 $end
$var reg 1 , done $end
$var reg 1 ) lda $end
$var reg 1 ( ldb $end
$var reg 1 $ sel1 $end
$var reg 1 # sel2 $end
$var reg 1 " sel_in $end
$var reg 3 7 state [2:0] $end
$upscope $end
$scope module DH $end
$var wire 1 - clk $end
$var wire 16 8 data_in [15:0] $end
$var wire 1 ) lda $end
$var wire 1 ( ldb $end
$var wire 16 9 result1 [15:0] $end
$var wire 16 : result2 [15:0] $end
$var wire 1 $ sel1 $end
$var wire 1 # sel2 $end
$var wire 1 " sel_in $end
$var wire 16 ; subout [15:0] $end
$var wire 1 ' lt $end
$var wire 1 * gt $end
$var wire 1 + et $end
$var wire 16 < data [15:0] $end
$var wire 16 = bout [15:0] $end
$var wire 16 > b [15:0] $end
$var wire 16 ? aout [15:0] $end
$var wire 16 @ a [15:0] $end
$scope module A $end
$var wire 1 - clk $end
$var wire 1 ) lda $end
$var wire 16 A a [15:0] $end
$var reg 16 B aout [15:0] $end
$upscope $end
$scope module B $end
$var wire 1 - clk $end
$var wire 1 ( lda $end
$var wire 16 C a [15:0] $end
$var reg 16 D aout [15:0] $end
$upscope $end
$scope module C $end
$var wire 16 E aout [15:0] $end
$var wire 16 F bout [15:0] $end
$var wire 1 ' lt $end
$var wire 1 * gt $end
$var wire 1 + et $end
$upscope $end
$scope module M0 $end
$var wire 16 G in1 [15:0] $end
$var wire 16 H in2 [15:0] $end
$var wire 1 $ sel $end
$var wire 16 I out [15:0] $end
$upscope $end
$scope module M1 $end
$var wire 16 J in1 [15:0] $end
$var wire 16 K in2 [15:0] $end
$var wire 1 # sel $end
$var wire 16 L out [15:0] $end
$upscope $end
$scope module M2 $end
$var wire 16 M in2 [15:0] $end
$var wire 1 " sel $end
$var wire 16 N out [15:0] $end
$var wire 16 O in1 [15:0] $end
$upscope $end
$scope module S $end
$var wire 16 P a [15:0] $end
$var wire 16 Q b [15:0] $end
$var reg 16 R subout [15:0] $end
$upscope $end
$upscope $end
$upscope $end
$enddefinitions $end
$comment Show the parameter values. $end
$dumpall
b101 6
b100 5
b11 4
b10 3
b1 2
b0 1
$end
#0
$dumpvars
b0 R
b0 Q
b0 P
b0 O
bx N
bx M
b0 L
b0 K
b0 J
b0 I
b0 H
b0 G
b0 F
b0 E
b0 D
bx C
b0 B
bx A
b0 @
b0 ?
b0 >
b0 =
bx <
b0 ;
b0 :
b0 9
bx 8
bx 7
bx 0
x/
bx .
0-
x,
1+
0*
x)
x(
0'
b0 &
b0 %
x$
x#
x"
bx !
$end
#3
1/
#5
0,
0"
0#
0$
0(
0)
b0 !
b0 0
b0 7
1-
#10
0-
#15
1)
b1 !
b1 0
b1 7
1-
#17
b111 <
b111 A
b111 C
b111 N
b111 .
b111 8
b111 M
#20
0-
#25
1(
0)
1*
0+
b111 &
b111 9
b111 ?
b111 B
b111 E
b111 G
b111 J
b10 !
b10 0
b10 7
1-
#27
b11 <
b11 A
b11 C
b11 N
b11 .
b11 8
b11 M
#30
0-
#35
b11 @
b11 I
b11 P
b11 >
b11 L
b11 Q
b11 %
b11 :
b11 =
b11 D
b11 F
b11 H
b11 K
1-
#37
b100 ;
b100 O
b100 R
b100 <
b100 A
b100 C
b100 N
b111 @
b111 I
b111 P
1"
1$
0(
1)
b100 !
b100 0
b100 7
#40
0-
#45
b1 <
b1 A
b1 C
b1 N
b1 ;
b1 O
b1 R
b100 @
b100 I
b100 P
b100 &
b100 9
b100 ?
b100 B
b100 E
b100 G
b100 J
1-
#50
0-
#55
b1111111111111110 <
b1111111111111110 A
b1111111111111110 C
b1111111111111110 N
b1111111111111110 ;
b1111111111111110 O
b1111111111111110 R
b1 @
b1 I
b1 P
1'
0*
b1 &
b1 9
b1 ?
b1 B
b1 E
b1 G
b1 J
1-
#57
b10 <
b10 A
b10 C
b10 N
b10 ;
b10 O
b10 R
b1 >
b1 L
b1 Q
b11 @
b11 I
b11 P
1#
0$
1(
0)
b11 !
b11 0
b11 7
#60
0-
#65
b1 <
b1 A
b1 C
b1 N
b1 ;
b1 O
b1 R
b10 @
b10 I
b10 P
b10 %
b10 :
b10 =
b10 D
b10 F
b10 H
b10 K
1-
#70
0-
#75
b0 <
b0 A
b0 C
b0 N
b0 ;
b0 O
b0 R
b1 @
b1 I
b1 P
0'
1+
b1 %
b1 :
b1 =
b1 D
b1 F
b1 H
b1 K
1-
#77
b11 <
b11 A
b11 C
b11 N
1,
0"
0#
0(
b101 !
b101 0
b101 7
